llm_huggingface.py
llm_huggingface-0.0.1.dist-info/LICENSE
llm_huggingface-0.0.1.dist-info/METADATA
llm_huggingface-0.0.1.dist-info/WHEEL
llm_huggingface-0.0.1.dist-info/entry_points.txt
llm_huggingface-0.0.1.dist-info/top_level.txt
llm_huggingface-0.0.1.dist-info/RECORD
