Metadata-Version: 2.1
Name: llm-huggingface
Version: 0.0.1
Summary: LLM plugin providing access to the huggingface inference API
Author: Andres EM
License: Apache-2.0
Classifier: License :: OSI Approved :: Apache Software License
Requires-Python: >=3.8
License-File: LICENSE
Requires-Dist: click
Requires-Dist: llm
Requires-Dist: requests
